design.sv
`timescale 1ns/1ps

module cache(
  input[7:0] addr,
  input clk, rst,
  output[7:0] out
);
  
  reg[7:0] RAM_data[0:255];          // RAM
  reg[2:0] ml_seq[0:7];				// Most used, Least used sequence
  reg[7:0] data_mem[0:7]; 		// Cache memory
  reg[7:0] tag[0:7];			// Cache Tag (address)
  //reg[7:0] valid_data;			// Valid data in cache memory
  reg[0:7] valid_seq;			// Valid element in ml_seq and cache memory
  reg[3:0] seq_cnt;				// Number of elements used in cache memory
  reg[7:0] op;					// Output register
  reg[7:0] tmp, tmp2, tmp3;
  
  integer i, j, k, cnt=0, break_loop = 0;
  
  assign out = op;
  
  initial
    begin
      $dumpfile("dump.vcd");
      $dumpvars(1,cache);
    end
  
  initial
    begin
      for(i=0;i<256;i=i+1)
        begin
          RAM_data[i] = i;
        end
    end
  
  initial
    begin
      for(j=0;j<8;j=j+1)
        begin
          ml_seq[j] = 0;
          data_mem[j] = 0;
          tag[j] = 0;
          valid_seq[j] = 0;
        end
    end
  
  always @(*)
    begin
      if (rst == 1'b0)
        begin
          for(j=0;j<8;j=j+1)
            begin
              ml_seq[j] = 0;
              data_mem[j] = 0;
              tag[j] = 0;
              valid_seq[j] = 0;
              cnt=0;
            end
        end
    end
  
  always @(negedge clk)
    begin
      if(rst == 1'b1)
        begin
          // HIT
          cnt=0;
          break_loop = 0;
          for(i=0;i<8 && break_loop == 0;i=i+1)
            begin
              if (addr == tag[i])
                begin
                  $display($realtime);
                  $display("HIT");
                  op = data_mem[i];
                  cnt = cnt-1; 
                  break_loop = 1;
                  for(j=i;j<seq_cnt && j<7;j=j+1)
                    begin
                      tmp = ml_seq[j];
                      ml_seq[j] = ml_seq[j+1];
                      ml_seq[j+1] = tmp;
                      tmp2 = data_mem[j];
                      data_mem[j] = data_mem[j+1];
                      data_mem[j+1] = tmp2;
                      tmp3 = tag[j];
                      tag[j] = tag[j+1];
                      tag[j+1] = tmp3;
                    end
                end
              cnt = cnt + 1;
            end 
          
          // MISS
          if(cnt == 8)
            begin
              $display($realtime);
              $display("MISS");
              if (seq_cnt == 4'b1111 && (addr[0] == 1'b1 || addr[0] == 1'b0))
                begin
                  tag[0] = addr;
                  data_mem[0] = RAM_data[addr];
                  ml_seq[0] = 0;
                  valid_seq[0] = 1;
                  op = RAM_data[addr];
                end

              else if (seq_cnt != 4'b0111 && (addr[0] == 1'b1 || addr[0] == 1'b0))
                begin
                  tag[seq_cnt[2:0]+1] = addr;
                  data_mem[seq_cnt[2:0]+1] = RAM_data[addr];
                  ml_seq[seq_cnt[2:0]+1] = seq_cnt[2:0]+1;
                  valid_seq[seq_cnt[2:0]+1] = 1;
                  op = RAM_data[addr];
                end
              else if(addr[0] == 1'b0 || addr[0] == 1'b1)
                begin
                  tag[0] = addr;
                  data_mem[0] = RAM_data[addr];
                  op = RAM_data[addr];
                  for(j=0;j<7;j=j+1)
                    begin
                      tmp = ml_seq[j];
                      ml_seq[j] = ml_seq[j+1];
                      ml_seq[j+1] = tmp;
                      tmp2 = data_mem[j];
                      data_mem[j] = data_mem[j+1];
                      data_mem[j+1] = tmp2;
                      tmp3 = tag[j];
                      tag[j] = tag[j+1];
                      tag[j+1] = tmp3;
                    end
                end
            end
        end    
    end
   
  always @(valid_seq)
    begin
      if (valid_seq[7] == 1'b1)
        seq_cnt = 4'b0111;
      else if(valid_seq[6] == 1'b1)
        seq_cnt = 4'b0110;
      else if(valid_seq[5] == 1'b1)
        seq_cnt = 4'b0101;
      else if(valid_seq[4] == 1'b1)
        seq_cnt = 4'b0100;
      else if(valid_seq[3] == 1'b1)
        seq_cnt = 4'b0011;
      else if(valid_seq[2] == 1'b1)
        seq_cnt = 4'b0010;
      else if(valid_seq[1] == 1'b1)
        seq_cnt = 4'b0001;
      else if(valid_seq[0] == 1'b1)
        seq_cnt = 4'b0000;
      else if(valid_seq[0] == 1'b0)
        seq_cnt = 4'b1111;
      else
        seq_cnt = 4'b1000;
    end    
endmodule

testbench.sv
`timescale 1ns/1ps
module tb;
  reg clk, rst;
  reg[7:0] addr;
  wire[7:0] out;  
  
  cache c1(.addr(addr),
           .clk(clk),
           .rst(rst),
           .out(out)
          );
  
  always #5 clk = ~clk;
  
  initial
    begin
      clk = 1'b0;
      rst = 1'b0;
      #10
      
      rst = 1'b1;      
      addr = 8'd10;
      #20
      
      addr = 8'd11;
      #20
      
      addr = 8'd12;
      #20
      
      addr = 8'd13;     
      #20
      
      addr = 8'd14;
      #20
      
      addr = 8'd12;
      #20
      
      addr = 8'd15;
      #20
      
      addr = 8'd16;
      #20
      
      addr = 8'd17;
      #20
      
      addr = 8'd18;
      #20
      
      addr = 8'd19;
      #100
      
      
      $finish;
    end
endmodule

dump.vcd
$date
	Thu Mar 18 11:13:06 2021
$end
$version
	Icarus Verilog
$end
$timescale
	1ps
$end
$scope module tb $end
$scope module c1 $end
$var wire 8 ! addr [7:0] $end
$var wire 1 " clk $end
$var wire 8 # out [7:0] $end
$var wire 1 $ rst $end
$var integer 32 % break_loop [31:0] $end
$var integer 32 & cnt [31:0] $end
$var integer 32 ' i [31:0] $end
$var integer 32 ( j [31:0] $end
$var reg 8 ) op [7:0] $end
$var reg 4 * seq_cnt [3:0] $end
$var reg 8 + tmp [7:0] $end
$var reg 8 , tmp2 [7:0] $end
$var reg 8 - tmp3 [7:0] $end
$var reg 8 . valid_seq [0:7] $end
$upscope $end
$upscope $end
$enddefinitions $end
#0
$dumpvars
b0 .
bx -
bx ,
bx +
b1111 *
bx )
b1000 (
b100000000 '
b0 &
b0 %
0$
bx #
0"
bx !
$end
#5000
1"
#10000
b0 *
b1010 )
b1010 #
b10000000 .
b1000 &
b1000 '
0"
b1010 !
1$
#15000
1"
#20000
b0 (
b1 %
b1 '
b0 &
0"
#25000
1"
#30000
b1 *
b1011 )
b1011 #
b11000000 .
b1000 &
b1000 '
b0 %
0"
b1011 !
#35000
1"
#40000
b1 (
b1 %
b10 '
b1 &
0"
#45000
1"
#50000
b10 *
b1100 )
b1100 #
b11100000 .
b1000 '
b0 %
b1000 &
0"
b1100 !
#55000
1"
#60000
b10 (
b1 %
b11 '
b10 &
0"
#65000
1"
#70000
b11 *
b1101 )
b1101 #
b11110000 .
b1000 '
b0 %
b1000 &
0"
b1101 !
#75000
1"
#80000
b11 (
b1 %
b100 '
b11 &
0"
#85000
1"
#90000
b100 *
b1110 )
b1110 #
b11111000 .
b1000 '
b0 %
b1000 &
0"
b1110 !
#95000
1"
#100000
b100 (
b1 %
b101 '
b100 &
0"
#105000
1"
#110000
b1100 -
b1100 ,
b10 +
b100 (
b1100 )
b1100 #
b11 '
b1 %
b10 &
0"
b1100 !
#115000
1"
#120000
b101 '
b1 %
b100 &
0"
#125000
1"
#130000
b101 *
b1111 )
b1111 #
b11111100 .
b1000 '
b0 %
b1000 &
0"
b1111 !
#135000
1"
#140000
b101 (
b1 %
b110 '
b101 &
0"
#145000
1"
#150000
b110 *
b10000 )
b10000 #
b11111110 .
b1000 '
b0 %
b1000 &
0"
b10000 !
#155000
1"
#160000
b110 (
b1 %
b111 '
b110 &
0"
#165000
1"
#170000
b111 *
b10001 )
b10001 #
b11111111 .
b1000 '
b0 %
b1000 &
0"
b10001 !
#175000
1"
#180000
b111 (
b1 %
b1000 '
b111 &
0"
#185000
1"
#190000
b10010 -
b10010 ,
b0 +
b111 (
b10010 )
b10010 #
b1000 '
b0 %
b1000 &
0"
b10010 !
#195000
1"
#200000
b1 %
b1000 '
b111 &
0"
#205000
1"
#210000
b10011 -
b10011 ,
b1 +
b111 (
b10011 )
b10011 #
b1000 '
b0 %
b1000 &
0"
b10011 !
#215000
1"
#220000
b1 %
b1000 '
b111 &
0"
#225000
1"
#230000
b1000 '
b1 %
b111 &
0"
#235000
1"
#240000
b1000 '
b1 %
b111 &
0"
#245000
1"
#250000
b1000 '
b1 %
b111 &
0"
#255000
1"
#260000
b1000 '
b1 %
b111 &
0"
#265000
1"
#270000
b1000 '
b1 %
b111 &
0"
#275000
1"
#280000
b1000 '
b1 %
b111 &
0"
#285000
1"
#290000
b1000 '
b1 %
b111 &
0"
#295000
1"
#300000
b1000 '
b1 %
b111 &
0"
#305000
1"
#310000
b111 '
b0 %
b111 &
0"
